CHANGES.txt
LICENSE.txt
MANIFEST.in
README.rst
setup.cfg
setup.py
docs/source/conf.py
docs/source/general.rst
docs/source/getting_started.rst
docs/source/index.rst
docs/source/install.rst
docs/source/retrieval.rst
docs/source/upload.rst
gnodeclient/__init__.py
gnodeclient/conf.py
gnodeclient/session.py
gnodeclient/tools.py
gnodeclient.egg-info/PKG-INFO
gnodeclient.egg-info/SOURCES.txt
gnodeclient.egg-info/dependency_links.txt
gnodeclient.egg-info/not-zip-safe
gnodeclient.egg-info/requires.txt
gnodeclient.egg-info/top_level.txt
gnodeclient/examples/__init__.py
gnodeclient/examples/overview.py
gnodeclient/examples/use_case.py
gnodeclient/examples/use_case_core.py
gnodeclient/model/__init__.py
gnodeclient/model/model_fields.py
gnodeclient/model/models.py
gnodeclient/result/__init__.py
gnodeclient/result/adapt_mixins.py
gnodeclient/result/adapt_neo.py
gnodeclient/result/adapt_odml.py
gnodeclient/result/result_driver.py
gnodeclient/store/__init__.py
gnodeclient/store/basic_store.py
gnodeclient/store/cache_store.py
gnodeclient/store/caching_rest_store.py
gnodeclient/store/convert.py
gnodeclient/store/dumper.py
gnodeclient/store/rest_store.py
gnodeclient/test/__init__.py
gnodeclient/test/quick.py
gnodeclient/test/test_all.py
gnodeclient/test/test_data.py
gnodeclient/test/test_dumper.py
gnodeclient/test/test_hdfio.py
gnodeclient/test/test_remote.py
gnodeclient/util/__init__.py
gnodeclient/util/cache.py
gnodeclient/util/declarative_models.py
gnodeclient/util/hdfio.py
gnodeclient/util/helper.py
gnodeclient/util/proxy.py