Metadata-Version: 1.1
Name: gnodeclient
Version: 0.4.0
Summary: Client for the G-Node REST API.
Home-page: https://github.com/G-Node/python-gnode-client
Author: A. Stoewer, A. Sobolev
Author-email: adrian.stoewer@rz.ifi.lmu.de
License: LGPL
Platform: UNKNOWN
Classifier: Development Status :: 4 - Beta
Classifier: Programming Language :: Python
Classifier: Programming Language :: Python :: 2.6
Classifier: Programming Language :: Python :: 2.7
Classifier: Programming Language :: Python :: 3
Classifier: Programming Language :: Python :: 3.1
Classifier: Programming Language :: Python :: 3.2
